{"title":"Lua","properties":{"Lua.workspace.maxPreload":{"default":5000,"markdownDescription":"%config.workspace.maxPreload%","type":"integer","scope":"resource"},"Lua.hover.expandAlias":{"default":true,"markdownDescription":"%config.hover.expandAlias%","type":"boolean","scope":"resource"},"Lua.workspace.preloadFileSize":{"default":500,"markdownDescription":"%config.workspace.preloadFileSize%","type":"integer","scope":"resource"},"Lua.hover.previewFields":{"default":50,"markdownDescription":"%config.hover.previewFields%","type":"integer","scope":"resource"},"Lua.workspace.useGitIgnore":{"default":true,"markdownDescription":"%config.workspace.useGitIgnore%","type":"boolean","scope":"resource"},"Lua.hover.viewNumber":{"default":true,"markdownDescription":"%config.hover.viewNumber%","type":"boolean","scope":"resource"},"Lua.workspace.userThirdParty":{"default":[],"items":{"type":"string"},"scope":"resource","markdownDescription":"%config.workspace.userThirdParty%","type":"array"},"Lua.hover.viewString":{"default":true,"markdownDescription":"%config.hover.viewString%","type":"boolean","scope":"resource"},"Lua.hover.viewStringMax":{"default":1000,"markdownDescription":"%config.hover.viewStringMax%","type":"integer","scope":"resource"},"Lua.nameStyle.config":{"default":{},"additionalProperties":false,"scope":"resource","type":"object","markdownDescription":"%config.nameStyle.config%","title":"config","patternProperties":{".*":{"type":["string","array"]}}},"Lua.runtime.builtin":{"additionalProperties":false,"properties":{"jit":{"default":"default","type":"string","enum":["default","enable","disable"],"description":"%config.runtime.builtin.jit%"},"basic":{"default":"default","type":"string","enum":["default","enable","disable"],"description":"%config.runtime.builtin.basic%"},"builtin":{"default":"default","type":"string","enum":["default","enable","disable"],"description":"%config.runtime.builtin.builtin%"},"string.buffer":{"default":"default","type":"string","enum":["default","enable","disable"],"description":"%config.runtime.builtin.string.buffer%"},"math":{"default":"default","type":"string","enum":["default","enable","disable"],"description":"%config.runtime.builtin.math%"},"jit.profile":{"default":"default","type":"string","enum":["default","enable","disable"],"description":"%config.runtime.builtin.jit.profile%"},"jit.util":{"default":"default","type":"string","enum":["default","enable","disable"],"description":"%config.runtime.builtin.jit.util%"},"string":{"default":"default","type":"string","enum":["default","enable","disable"],"description":"%config.runtime.builtin.string%"},"os":{"default":"default","type":"string","enum":["default","enable","disable"],"description":"%config.runtime.builtin.os%"},"coroutine":{"default":"default","type":"string","enum":["default","enable","disable"],"description":"%config.runtime.builtin.coroutine%"},"bit32":{"default":"default","type":"string","enum":["default","enable","disable"],"description":"%config.runtime.builtin.bit32%"},"bit":{"default":"default","type":"string","enum":["default","enable","disable"],"description":"%config.runtime.builtin.bit%"},"table.clear":{"default":"default","type":"string","enum":["default","enable","disable"],"description":"%config.runtime.builtin.table.clear%"},"io":{"default":"default","type":"string","enum":["default","enable","disable"],"description":"%config.runtime.builtin.io%"},"utf8":{"default":"default","type":"string","enum":["default","enable","disable"],"description":"%config.runtime.builtin.utf8%"},"package":{"default":"default","type":"string","enum":["default","enable","disable"],"description":"%config.runtime.builtin.package%"},"table.new":{"default":"default","type":"string","enum":["default","enable","disable"],"description":"%config.runtime.builtin.table.new%"},"table":{"default":"default","type":"string","enum":["default","enable","disable"],"description":"%config.runtime.builtin.table%"},"debug":{"default":"default","type":"string","enum":["default","enable","disable"],"description":"%config.runtime.builtin.debug%"},"ffi":{"default":"default","type":"string","enum":["default","enable","disable"],"description":"%config.runtime.builtin.ffi%"}},"scope":"resource","markdownDescription":"%config.runtime.builtin%","title":"builtin","type":"object"},"Lua.runtime.plugin":{"markdownDescription":"%config.runtime.plugin%","type":["string","array"],"scope":"resource"},"Lua.misc.executablePath":{"default":"","markdownDescription":"%config.misc.executablePath%","type":"string","scope":"resource"},"Lua.misc.parameters":{"default":[],"items":{"type":"string"},"scope":"resource","markdownDescription":"%config.misc.parameters%","type":"array"},"Lua.diagnostics.severity":{"additionalProperties":false,"properties":{"lowercase-global":{"default":"Information","type":"string","enum":["Error","Warning","Information","Hint","Error!","Warning!","Information!","Hint!"],"description":"%config.diagnostics.lowercase-global%"},"unused-vararg":{"default":"Hint","type":"string","enum":["Error","Warning","Information","Hint","Error!","Warning!","Information!","Hint!"],"description":"%config.diagnostics.unused-vararg%"},"unused-local":{"default":"Hint","type":"string","enum":["Error","Warning","Information","Hint","Error!","Warning!","Information!","Hint!"],"description":"%config.diagnostics.unused-local%"},"unused-label":{"default":"Hint","type":"string","enum":["Error","Warning","Information","Hint","Error!","Warning!","Information!","Hint!"],"description":"%config.diagnostics.unused-label%"},"unused-function":{"default":"Hint","type":"string","enum":["Error","Warning","Information","Hint","Error!","Warning!","Information!","Hint!"],"description":"%config.diagnostics.unused-function%"},"missing-global-doc":{"default":"Warning","type":"string","enum":["Error","Warning","Information","Hint","Error!","Warning!","Information!","Hint!"],"description":"%config.diagnostics.missing-global-doc%"},"unknown-operator":{"default":"Warning","type":"string","enum":["Error","Warning","Information","Hint","Error!","Warning!","Information!","Hint!"],"description":"%config.diagnostics.unknown-operator%"},"unknown-diag-code":{"default":"Warning","type":"string","enum":["Error","Warning","Information","Hint","Error!","Warning!","Information!","Hint!"],"description":"%config.diagnostics.unknown-diag-code%"},"unknown-cast-variable":{"default":"Warning","type":"string","enum":["Error","Warning","Information","Hint","Error!","Warning!","Information!","Hint!"],"description":"%config.diagnostics.unknown-cast-variable%"},"undefined-global":{"default":"Warning","type":"string","enum":["Error","Warning","Information","Hint","Error!","Warning!","Information!","Hint!"],"description":"%config.diagnostics.undefined-global%"},"undefined-field":{"default":"Warning","type":"string","enum":["Error","Warning","Information","Hint","Error!","Warning!","Information!","Hint!"],"description":"%config.diagnostics.undefined-field%"},"undefined-env-child":{"default":"Information","type":"string","enum":["Error","Warning","Information","Hint","Error!","Warning!","Information!","Hint!"],"description":"%config.diagnostics.undefined-env-child%"},"undefined-doc-param":{"default":"Warning","type":"string","enum":["Error","Warning","Information","Hint","Error!","Warning!","Information!","Hint!"],"description":"%config.diagnostics.undefined-doc-param%"},"undefined-doc-name":{"default":"Warning","type":"string","enum":["Error","Warning","Information","Hint","Error!","Warning!","Information!","Hint!"],"description":"%config.diagnostics.undefined-doc-name%"},"undefined-doc-class":{"default":"Warning","type":"string","enum":["Error","Warning","Information","Hint","Error!","Warning!","Information!","Hint!"],"description":"%config.diagnostics.undefined-doc-class%"},"unbalanced-assignments":{"default":"Warning","type":"string","enum":["Error","Warning","Information","Hint","Error!","Warning!","Information!","Hint!"],"description":"%config.diagnostics.unbalanced-assignments%"},"trailing-space":{"default":"Hint","type":"string","enum":["Error","Warning","Information","Hint","Error!","Warning!","Information!","Hint!"],"description":"%config.diagnostics.trailing-space%"},"spell-check":{"default":"Information","type":"string","enum":["Error","Warning","Information","Hint","Error!","Warning!","Information!","Hint!"],"description":"%config.diagnostics.spell-check%"},"return-type-mismatch":{"default":"Warning","type":"string","enum":["Error","Warning","Information","Hint","Error!","Warning!","Information!","Hint!"],"description":"%config.diagnostics.return-type-mismatch%"},"redundant-value":{"default":"Warning","type":"string","enum":["Error","Warning","Information","Hint","Error!","Warning!","Information!","Hint!"],"description":"%config.diagnostics.redundant-value%"},"missing-fields":{"default":"Warning","type":"string","enum":["Error","Warning","Information","Hint","Error!","Warning!","Information!","Hint!"],"description":"%config.diagnostics.missing-fields%"},"not-yieldable":{"default":"Warning","type":"string","enum":["Error","Warning","Information","Hint","Error!","Warning!","Information!","Hint!"],"description":"%config.diagnostics.not-yieldable%"},"redundant-parameter":{"default":"Warning","type":"string","enum":["Error","Warning","Information","Hint","Error!","Warning!","Information!","Hint!"],"description":"%config.diagnostics.redundant-parameter%"},"ambiguity-1":{"default":"Warning","type":"string","enum":["Error","Warning","Information","Hint","Error!","Warning!","Information!","Hint!"],"description":"%config.diagnostics.ambiguity-1%"},"param-type-mismatch":{"default":"Warning","type":"string","enum":["Error","Warning","Information","Hint","Error!","Warning!","Information!","Hint!"],"description":"%config.diagnostics.param-type-mismatch%"},"redefined-local":{"default":"Hint","type":"string","enum":["Error","Warning","Information","Hint","Error!","Warning!","Information!","Hint!"],"description":"%config.diagnostics.redefined-local%"},"assign-type-mismatch":{"default":"Warning","type":"string","enum":["Error","Warning","Information","Hint","Error!","Warning!","Information!","Hint!"],"description":"%config.diagnostics.assign-type-mismatch%"},"await-in-sync":{"default":"Warning","type":"string","enum":["Error","Warning","Information","Hint","Error!","Warning!","Information!","Hint!"],"description":"%config.diagnostics.await-in-sync%"},"redundant-return":{"default":"Hint","type":"string","enum":["Error","Warning","Information","Hint","Error!","Warning!","Information!","Hint!"],"description":"%config.diagnostics.redundant-return%"},"redundant-return-value":{"default":"Warning","type":"string","enum":["Error","Warning","Information","Hint","Error!","Warning!","Information!","Hint!"],"description":"%config.diagnostics.redundant-return-value%"},"cast-local-type":{"default":"Warning","type":"string","enum":["Error","Warning","Information","Hint","Error!","Warning!","Information!","Hint!"],"description":"%config.diagnostics.cast-local-type%"},"cast-type-mismatch":{"default":"Warning","type":"string","enum":["Error","Warning","Information","Hint","Error!","Warning!","Information!","Hint!"],"description":"%config.diagnostics.cast-type-mismatch%"},"circle-doc-class":{"default":"Warning","type":"string","enum":["Error","Warning","Information","Hint","Error!","Warning!","Information!","Hint!"],"description":"%config.diagnostics.circle-doc-class%"},"close-non-object":{"default":"Warning","type":"string","enum":["Error","Warning","Information","Hint","Error!","Warning!","Information!","Hint!"],"description":"%config.diagnostics.close-non-object%"},"code-after-break":{"default":"Hint","type":"string","enum":["Error","Warning","Information","Hint","Error!","Warning!","Information!","Hint!"],"description":"%config.diagnostics.code-after-break%"},"codestyle-check":{"default":"Warning","type":"string","enum":["Error","Warning","Information","Hint","Error!","Warning!","Information!","Hint!"],"description":"%config.diagnostics.codestyle-check%"},"count-down-loop":{"default":"Warning","type":"string","enum":["Error","Warning","Information","Hint","Error!","Warning!","Information!","Hint!"],"description":"%config.diagnostics.count-down-loop%"},"different-requires":{"default":"Warning","type":"string","enum":["Error","Warning","Information","Hint","Error!","Warning!","Information!","Hint!"],"description":"%config.diagnostics.different-requires%"},"discard-returns":{"default":"Warning","type":"string","enum":["Error","Warning","Information","Hint","Error!","Warning!","Information!","Hint!"],"description":"%config.diagnostics.discard-returns%"},"doc-field-no-class":{"default":"Warning","type":"string","enum":["Error","Warning","Information","Hint","Error!","Warning!","Information!","Hint!"],"description":"%config.diagnostics.doc-field-no-class%"},"duplicate-doc-alias":{"default":"Warning","type":"string","enum":["Error","Warning","Information","Hint","Error!","Warning!","Information!","Hint!"],"description":"%config.diagnostics.duplicate-doc-alias%"},"duplicate-doc-field":{"default":"Warning","type":"string","enum":["Error","Warning","Information","Hint","Error!","Warning!","Information!","Hint!"],"description":"%config.diagnostics.duplicate-doc-field%"},"duplicate-doc-param":{"default":"Warning","type":"string","enum":["Error","Warning","Information","Hint","Error!","Warning!","Information!","Hint!"],"description":"%config.diagnostics.duplicate-doc-param%"},"duplicate-index":{"default":"Warning","type":"string","enum":["Error","Warning","Information","Hint","Error!","Warning!","Information!","Hint!"],"description":"%config.diagnostics.duplicate-index%"},"duplicate-set-field":{"default":"Warning","type":"string","enum":["Error","Warning","Information","Hint","Error!","Warning!","Information!","Hint!"],"description":"%config.diagnostics.duplicate-set-field%"},"empty-block":{"default":"Hint","type":"string","enum":["Error","Warning","Information","Hint","Error!","Warning!","Information!","Hint!"],"description":"%config.diagnostics.empty-block%"},"name-style-check":{"default":"Warning","type":"string","enum":["Error","Warning","Information","Hint","Error!","Warning!","Information!","Hint!"],"description":"%config.diagnostics.name-style-check%"},"need-check-nil":{"default":"Warning","type":"string","enum":["Error","Warning","Information","Hint","Error!","Warning!","Information!","Hint!"],"description":"%config.diagnostics.need-check-nil%"},"newfield-call":{"default":"Warning","type":"string","enum":["Error","Warning","Information","Hint","Error!","Warning!","Information!","Hint!"],"description":"%config.diagnostics.newfield-call%"},"newline-call":{"default":"Warning","type":"string","enum":["Error","Warning","Information","Hint","Error!","Warning!","Information!","Hint!"],"description":"%config.diagnostics.newline-call%"},"no-unknown":{"default":"Warning","type":"string","enum":["Error","Warning","Information","Hint","Error!","Warning!","Information!","Hint!"],"description":"%config.diagnostics.no-unknown%"},"missing-return":{"default":"Warning","type":"string","enum":["Error","Warning","Information","Hint","Error!","Warning!","Information!","Hint!"],"description":"%config.diagnostics.missing-return%"},"unreachable-code":{"default":"Hint","type":"string","enum":["Error","Warning","Information","Hint","Error!","Warning!","Information!","Hint!"],"description":"%config.diagnostics.unreachable-code%"},"deprecated":{"default":"Warning","type":"string","enum":["Error","Warning","Information","Hint","Error!","Warning!","Information!","Hint!"],"description":"%config.diagnostics.deprecated%"},"missing-parameter":{"default":"Warning","type":"string","enum":["Error","Warning","Information","Hint","Error!","Warning!","Information!","Hint!"],"description":"%config.diagnostics.missing-parameter%"},"global-element":{"default":"Warning","type":"string","enum":["Error","Warning","Information","Hint","Error!","Warning!","Information!","Hint!"],"description":"%config.diagnostics.global-element%"},"global-in-nil-env":{"default":"Warning","type":"string","enum":["Error","Warning","Information","Hint","Error!","Warning!","Information!","Hint!"],"description":"%config.diagnostics.global-in-nil-env%"},"incomplete-signature-doc":{"default":"Warning","type":"string","enum":["Error","Warning","Information","Hint","Error!","Warning!","Information!","Hint!"],"description":"%config.diagnostics.incomplete-signature-doc%"},"missing-local-export-doc":{"default":"Warning","type":"string","enum":["Error","Warning","Information","Hint","Error!","Warning!","Information!","Hint!"],"description":"%config.diagnostics.missing-local-export-doc%"},"inject-field":{"default":"Warning","type":"string","enum":["Error","Warning","Information","Hint","Error!","Warning!","Information!","Hint!"],"description":"%config.diagnostics.inject-field%"},"invisible":{"default":"Warning","type":"string","enum":["Error","Warning","Information","Hint","Error!","Warning!","Information!","Hint!"],"description":"%config.diagnostics.invisible%"},"missing-return-value":{"default":"Warning","type":"string","enum":["Error","Warning","Information","Hint","Error!","Warning!","Information!","Hint!"],"description":"%config.diagnostics.missing-return-value%"}},"scope":"resource","markdownDescription":"%config.diagnostics.severity%","title":"severity","type":"object"},"Lua.runtime.fileEncoding":{"default":"utf8","markdownDescription":"%config.runtime.fileEncoding%","markdownEnumDescriptions":["%config.runtime.fileEncoding.utf8%","%config.runtime.fileEncoding.ansi%","%config.runtime.fileEncoding.utf16le%","%config.runtime.fileEncoding.utf16be%"],"enum":["utf8","ansi","utf16le","utf16be"],"scope":"resource","type":"string"},"Lua.diagnostics.unusedLocalExclude":{"default":[],"items":{"type":"string"},"scope":"resource","markdownDescription":"%config.diagnostics.unusedLocalExclude%","type":"array"},"Lua.diagnostics.workspaceDelay":{"default":3000,"markdownDescription":"%config.diagnostics.workspaceDelay%","type":"integer","scope":"resource"},"Lua.diagnostics.workspaceEvent":{"default":"OnSave","markdownDescription":"%config.diagnostics.workspaceEvent%","markdownEnumDescriptions":["%config.diagnostics.workspaceEvent.OnChange%","%config.diagnostics.workspaceEvent.OnSave%","%config.diagnostics.workspaceEvent.None%"],"enum":["OnChange","OnSave","None"],"scope":"resource","type":"string"},"Lua.runtime.meta":{"default":"${version} ${language} ${encoding}","markdownDescription":"%config.runtime.meta%","type":"string","scope":"resource"},"Lua.diagnostics.disableScheme":{"default":["git"],"items":{"type":"string"},"scope":"resource","markdownDescription":"%config.diagnostics.disableScheme%","type":"array"},"Lua.runtime.nonstandardSymbol":{"default":[],"items":{"type":"string","enum":["\/\/","\/**\/","`","+=","-=","*=","\/=","%=","^=","\/\/=","|=","&=","<<=",">>=","||","&&","!","!=","continue"]},"scope":"resource","markdownDescription":"%config.runtime.nonstandardSymbol%","type":"array"},"Lua.codeLens.enable":{"default":false,"markdownDescription":"%config.codeLens.enable%","type":"boolean","scope":"resource"},"Lua.diagnostics.globals":{"default":[],"items":{"type":"string"},"scope":"resource","markdownDescription":"%config.diagnostics.globals%","type":"array"},"Lua.completion.autoRequire":{"default":true,"markdownDescription":"%config.completion.autoRequire%","type":"boolean","scope":"resource"},"Lua.diagnostics.globalsRegex":{"default":[],"items":{"type":"string"},"scope":"resource","markdownDescription":"%config.diagnostics.globalsRegex%","type":"array"},"Lua.completion.callSnippet":{"default":"Disable","markdownDescription":"%config.completion.callSnippet%","markdownEnumDescriptions":["%config.completion.callSnippet.Disable%","%config.completion.callSnippet.Both%","%config.completion.callSnippet.Replace%"],"enum":["Disable","Both","Replace"],"scope":"resource","type":"string"},"Lua.diagnostics.groupFileStatus":{"additionalProperties":false,"properties":{"codestyle":{"default":"Fallback","type":"string","enum":["Any","Opened","None","Fallback"],"description":"%config.diagnostics.codestyle%"},"duplicate":{"default":"Fallback","type":"string","enum":["Any","Opened","None","Fallback"],"description":"%config.diagnostics.duplicate%"},"conventions":{"default":"Fallback","type":"string","enum":["Any","Opened","None","Fallback"],"description":"%config.diagnostics.conventions%"},"unused":{"default":"Fallback","type":"string","enum":["Any","Opened","None","Fallback"],"description":"%config.diagnostics.unused%"},"redefined":{"default":"Fallback","type":"string","enum":["Any","Opened","None","Fallback"],"description":"%config.diagnostics.redefined%"},"global":{"default":"Fallback","type":"string","enum":["Any","Opened","None","Fallback"],"description":"%config.diagnostics.global%"},"strict":{"default":"Fallback","type":"string","enum":["Any","Opened","None","Fallback"],"description":"%config.diagnostics.strict%"},"strong":{"default":"Fallback","type":"string","enum":["Any","Opened","None","Fallback"],"description":"%config.diagnostics.strong%"},"ambiguity":{"default":"Fallback","type":"string","enum":["Any","Opened","None","Fallback"],"description":"%config.diagnostics.ambiguity%"},"type-check":{"default":"Fallback","type":"string","enum":["Any","Opened","None","Fallback"],"description":"%config.diagnostics.type-check%"},"await":{"default":"Fallback","type":"string","enum":["Any","Opened","None","Fallback"],"description":"%config.diagnostics.await%"},"unbalanced":{"default":"Fallback","type":"string","enum":["Any","Opened","None","Fallback"],"description":"%config.diagnostics.unbalanced%"},"luadoc":{"default":"Fallback","type":"string","enum":["Any","Opened","None","Fallback"],"description":"%config.diagnostics.luadoc%"}},"scope":"resource","markdownDescription":"%config.diagnostics.groupFileStatus%","title":"groupFileStatus","type":"object"},"Lua.completion.displayContext":{"default":0,"markdownDescription":"%config.completion.displayContext%","type":"integer","scope":"resource"},"Lua.completion.enable":{"default":true,"markdownDescription":"%config.completion.enable%","type":"boolean","scope":"resource"},"Lua.completion.keywordSnippet":{"default":"Replace","markdownDescription":"%config.completion.keywordSnippet%","markdownEnumDescriptions":["%config.completion.keywordSnippet.Disable%","%config.completion.keywordSnippet.Both%","%config.completion.keywordSnippet.Replace%"],"enum":["Disable","Both","Replace"],"scope":"resource","type":"string"},"Lua.runtime.pluginArgs":{"markdownDescription":"%config.runtime.pluginArgs%","type":["array","object"],"scope":"resource"},"Lua.completion.postfix":{"default":"@","markdownDescription":"%config.completion.postfix%","type":"string","scope":"resource"},"Lua.completion.requireSeparator":{"default":".","markdownDescription":"%config.completion.requireSeparator%","type":"string","scope":"resource"},"Lua.runtime.unicodeName":{"default":false,"markdownDescription":"%config.runtime.unicodeName%","type":"boolean","scope":"resource"},"Lua.completion.showParams":{"default":true,"markdownDescription":"%config.completion.showParams%","type":"boolean","scope":"resource"},"Lua.runtime.version":{"default":"Lua 5.4","markdownDescription":"%config.runtime.version%","markdownEnumDescriptions":["%config.runtime.version.Lua 5.1%","%config.runtime.version.Lua 5.2%","%config.runtime.version.Lua 5.3%","%config.runtime.version.Lua 5.4%","%config.runtime.version.LuaJIT%"],"enum":["Lua 5.1","Lua 5.2","Lua 5.3","Lua 5.4","LuaJIT"],"scope":"resource","type":"string"},"Lua.completion.showWord":{"default":"Fallback","markdownDescription":"%config.completion.showWord%","markdownEnumDescriptions":["%config.completion.showWord.Enable%","%config.completion.showWord.Fallback%","%config.completion.showWord.Disable%"],"enum":["Enable","Fallback","Disable"],"scope":"resource","type":"string"},"Lua.diagnostics.groupSeverity":{"additionalProperties":false,"properties":{"codestyle":{"default":"Fallback","type":"string","enum":["Error","Warning","Information","Hint","Fallback"],"description":"%config.diagnostics.codestyle%"},"duplicate":{"default":"Fallback","type":"string","enum":["Error","Warning","Information","Hint","Fallback"],"description":"%config.diagnostics.duplicate%"},"conventions":{"default":"Fallback","type":"string","enum":["Error","Warning","Information","Hint","Fallback"],"description":"%config.diagnostics.conventions%"},"unused":{"default":"Fallback","type":"string","enum":["Error","Warning","Information","Hint","Fallback"],"description":"%config.diagnostics.unused%"},"redefined":{"default":"Fallback","type":"string","enum":["Error","Warning","Information","Hint","Fallback"],"description":"%config.diagnostics.redefined%"},"global":{"default":"Fallback","type":"string","enum":["Error","Warning","Information","Hint","Fallback"],"description":"%config.diagnostics.global%"},"strict":{"default":"Fallback","type":"string","enum":["Error","Warning","Information","Hint","Fallback"],"description":"%config.diagnostics.strict%"},"strong":{"default":"Fallback","type":"string","enum":["Error","Warning","Information","Hint","Fallback"],"description":"%config.diagnostics.strong%"},"ambiguity":{"default":"Fallback","type":"string","enum":["Error","Warning","Information","Hint","Fallback"],"description":"%config.diagnostics.ambiguity%"},"type-check":{"default":"Fallback","type":"string","enum":["Error","Warning","Information","Hint","Fallback"],"description":"%config.diagnostics.type-check%"},"await":{"default":"Fallback","type":"string","enum":["Error","Warning","Information","Hint","Fallback"],"description":"%config.diagnostics.await%"},"unbalanced":{"default":"Fallback","type":"string","enum":["Error","Warning","Information","Hint","Fallback"],"description":"%config.diagnostics.unbalanced%"},"luadoc":{"default":"Fallback","type":"string","enum":["Error","Warning","Information","Hint","Fallback"],"description":"%config.diagnostics.luadoc%"}},"scope":"resource","markdownDescription":"%config.diagnostics.groupSeverity%","title":"groupSeverity","type":"object"},"Lua.completion.workspaceWord":{"default":true,"markdownDescription":"%config.completion.workspaceWord%","type":"boolean","scope":"resource"},"Lua.diagnostics.ignoredFiles":{"default":"Opened","markdownDescription":"%config.diagnostics.ignoredFiles%","markdownEnumDescriptions":["%config.diagnostics.ignoredFiles.Enable%","%config.diagnostics.ignoredFiles.Opened%","%config.diagnostics.ignoredFiles.Disable%"],"enum":["Enable","Opened","Disable"],"scope":"resource","type":"string"},"Lua.semantic.annotation":{"default":true,"markdownDescription":"%config.semantic.annotation%","type":"boolean","scope":"resource"},"Lua.semantic.enable":{"default":true,"markdownDescription":"%config.semantic.enable%","type":"boolean","scope":"resource"},"Lua.doc.packageName":{"default":[],"items":{"type":"string"},"scope":"resource","markdownDescription":"%config.doc.packageName%","type":"array"},"Lua.semantic.keyword":{"default":false,"markdownDescription":"%config.semantic.keyword%","type":"boolean","scope":"resource"},"Lua.doc.privateName":{"default":[],"items":{"type":"string"},"scope":"resource","markdownDescription":"%config.doc.privateName%","type":"array"},"Lua.semantic.variable":{"default":true,"markdownDescription":"%config.semantic.variable%","type":"boolean","scope":"resource"},"Lua.format.defaultConfig":{"default":{},"additionalProperties":false,"scope":"resource","type":"object","markdownDescription":"%config.format.defaultConfig%","title":"defaultConfig","patternProperties":{".*":{"default":"","type":"string"}}},"Lua.signatureHelp.enable":{"default":true,"markdownDescription":"%config.signatureHelp.enable%","type":"boolean","scope":"resource"},"Lua.diagnostics.neededFileStatus":{"additionalProperties":false,"properties":{"lowercase-global":{"default":"Any","type":"string","enum":["Any","Opened","None","Any!","Opened!","None!"],"description":"%config.diagnostics.lowercase-global%"},"unused-vararg":{"default":"Opened","type":"string","enum":["Any","Opened","None","Any!","Opened!","None!"],"description":"%config.diagnostics.unused-vararg%"},"unused-local":{"default":"Opened","type":"string","enum":["Any","Opened","None","Any!","Opened!","None!"],"description":"%config.diagnostics.unused-local%"},"unused-label":{"default":"Opened","type":"string","enum":["Any","Opened","None","Any!","Opened!","None!"],"description":"%config.diagnostics.unused-label%"},"unused-function":{"default":"Opened","type":"string","enum":["Any","Opened","None","Any!","Opened!","None!"],"description":"%config.diagnostics.unused-function%"},"missing-global-doc":{"default":"None","type":"string","enum":["Any","Opened","None","Any!","Opened!","None!"],"description":"%config.diagnostics.missing-global-doc%"},"unknown-operator":{"default":"Any","type":"string","enum":["Any","Opened","None","Any!","Opened!","None!"],"description":"%config.diagnostics.unknown-operator%"},"unknown-diag-code":{"default":"Any","type":"string","enum":["Any","Opened","None","Any!","Opened!","None!"],"description":"%config.diagnostics.unknown-diag-code%"},"unknown-cast-variable":{"default":"Any","type":"string","enum":["Any","Opened","None","Any!","Opened!","None!"],"description":"%config.diagnostics.unknown-cast-variable%"},"undefined-global":{"default":"Any","type":"string","enum":["Any","Opened","None","Any!","Opened!","None!"],"description":"%config.diagnostics.undefined-global%"},"undefined-field":{"default":"Opened","type":"string","enum":["Any","Opened","None","Any!","Opened!","None!"],"description":"%config.diagnostics.undefined-field%"},"undefined-env-child":{"default":"Any","type":"string","enum":["Any","Opened","None","Any!","Opened!","None!"],"description":"%config.diagnostics.undefined-env-child%"},"undefined-doc-param":{"default":"Any","type":"string","enum":["Any","Opened","None","Any!","Opened!","None!"],"description":"%config.diagnostics.undefined-doc-param%"},"undefined-doc-name":{"default":"Any","type":"string","enum":["Any","Opened","None","Any!","Opened!","None!"],"description":"%config.diagnostics.undefined-doc-name%"},"undefined-doc-class":{"default":"Any","type":"string","enum":["Any","Opened","None","Any!","Opened!","None!"],"description":"%config.diagnostics.undefined-doc-class%"},"unbalanced-assignments":{"default":"Any","type":"string","enum":["Any","Opened","None","Any!","Opened!","None!"],"description":"%config.diagnostics.unbalanced-assignments%"},"trailing-space":{"default":"Opened","type":"string","enum":["Any","Opened","None","Any!","Opened!","None!"],"description":"%config.diagnostics.trailing-space%"},"spell-check":{"default":"None","type":"string","enum":["Any","Opened","None","Any!","Opened!","None!"],"description":"%config.diagnostics.spell-check%"},"return-type-mismatch":{"default":"Opened","type":"string","enum":["Any","Opened","None","Any!","Opened!","None!"],"description":"%config.diagnostics.return-type-mismatch%"},"redundant-value":{"default":"Any","type":"string","enum":["Any","Opened","None","Any!","Opened!","None!"],"description":"%config.diagnostics.redundant-value%"},"missing-fields":{"default":"Any","type":"string","enum":["Any","Opened","None","Any!","Opened!","None!"],"description":"%config.diagnostics.missing-fields%"},"not-yieldable":{"default":"None","type":"string","enum":["Any","Opened","None","Any!","Opened!","None!"],"description":"%config.diagnostics.not-yieldable%"},"redundant-parameter":{"default":"Any","type":"string","enum":["Any","Opened","None","Any!","Opened!","None!"],"description":"%config.diagnostics.redundant-parameter%"},"ambiguity-1":{"default":"Any","type":"string","enum":["Any","Opened","None","Any!","Opened!","None!"],"description":"%config.diagnostics.ambiguity-1%"},"param-type-mismatch":{"default":"Opened","type":"string","enum":["Any","Opened","None","Any!","Opened!","None!"],"description":"%config.diagnostics.param-type-mismatch%"},"redefined-local":{"default":"Opened","type":"string","enum":["Any","Opened","None","Any!","Opened!","None!"],"description":"%config.diagnostics.redefined-local%"},"assign-type-mismatch":{"default":"Opened","type":"string","enum":["Any","Opened","None","Any!","Opened!","None!"],"description":"%config.diagnostics.assign-type-mismatch%"},"await-in-sync":{"default":"None","type":"string","enum":["Any","Opened","None","Any!","Opened!","None!"],"description":"%config.diagnostics.await-in-sync%"},"redundant-return":{"default":"Opened","type":"string","enum":["Any","Opened","None","Any!","Opened!","None!"],"description":"%config.diagnostics.redundant-return%"},"redundant-return-value":{"default":"Any","type":"string","enum":["Any","Opened","None","Any!","Opened!","None!"],"description":"%config.diagnostics.redundant-return-value%"},"cast-local-type":{"default":"Opened","type":"string","enum":["Any","Opened","None","Any!","Opened!","None!"],"description":"%config.diagnostics.cast-local-type%"},"cast-type-mismatch":{"default":"Opened","type":"string","enum":["Any","Opened","None","Any!","Opened!","None!"],"description":"%config.diagnostics.cast-type-mismatch%"},"circle-doc-class":{"default":"Any","type":"string","enum":["Any","Opened","None","Any!","Opened!","None!"],"description":"%config.diagnostics.circle-doc-class%"},"close-non-object":{"default":"Any","type":"string","enum":["Any","Opened","None","Any!","Opened!","None!"],"description":"%config.diagnostics.close-non-object%"},"code-after-break":{"default":"Opened","type":"string","enum":["Any","Opened","None","Any!","Opened!","None!"],"description":"%config.diagnostics.code-after-break%"},"codestyle-check":{"default":"None","type":"string","enum":["Any","Opened","None","Any!","Opened!","None!"],"description":"%config.diagnostics.codestyle-check%"},"count-down-loop":{"default":"Any","type":"string","enum":["Any","Opened","None","Any!","Opened!","None!"],"description":"%config.diagnostics.count-down-loop%"},"different-requires":{"default":"Any","type":"string","enum":["Any","Opened","None","Any!","Opened!","None!"],"description":"%config.diagnostics.different-requires%"},"discard-returns":{"default":"Any","type":"string","enum":["Any","Opened","None","Any!","Opened!","None!"],"description":"%config.diagnostics.discard-returns%"},"doc-field-no-class":{"default":"Any","type":"string","enum":["Any","Opened","None","Any!","Opened!","None!"],"description":"%config.diagnostics.doc-field-no-class%"},"duplicate-doc-alias":{"default":"Any","type":"string","enum":["Any","Opened","None","Any!","Opened!","None!"],"description":"%config.diagnostics.duplicate-doc-alias%"},"duplicate-doc-field":{"default":"Any","type":"string","enum":["Any","Opened","None","Any!","Opened!","None!"],"description":"%config.diagnostics.duplicate-doc-field%"},"duplicate-doc-param":{"default":"Any","type":"string","enum":["Any","Opened","None","Any!","Opened!","None!"],"description":"%config.diagnostics.duplicate-doc-param%"},"duplicate-index":{"default":"Any","type":"string","enum":["Any","Opened","None","Any!","Opened!","None!"],"description":"%config.diagnostics.duplicate-index%"},"duplicate-set-field":{"default":"Opened","type":"string","enum":["Any","Opened","None","Any!","Opened!","None!"],"description":"%config.diagnostics.duplicate-set-field%"},"empty-block":{"default":"Opened","type":"string","enum":["Any","Opened","None","Any!","Opened!","None!"],"description":"%config.diagnostics.empty-block%"},"name-style-check":{"default":"None","type":"string","enum":["Any","Opened","None","Any!","Opened!","None!"],"description":"%config.diagnostics.name-style-check%"},"need-check-nil":{"default":"Opened","type":"string","enum":["Any","Opened","None","Any!","Opened!","None!"],"description":"%config.diagnostics.need-check-nil%"},"newfield-call":{"default":"Any","type":"string","enum":["Any","Opened","None","Any!","Opened!","None!"],"description":"%config.diagnostics.newfield-call%"},"newline-call":{"default":"Any","type":"string","enum":["Any","Opened","None","Any!","Opened!","None!"],"description":"%config.diagnostics.newline-call%"},"no-unknown":{"default":"None","type":"string","enum":["Any","Opened","None","Any!","Opened!","None!"],"description":"%config.diagnostics.no-unknown%"},"missing-return":{"default":"Any","type":"string","enum":["Any","Opened","None","Any!","Opened!","None!"],"description":"%config.diagnostics.missing-return%"},"unreachable-code":{"default":"Opened","type":"string","enum":["Any","Opened","None","Any!","Opened!","None!"],"description":"%config.diagnostics.unreachable-code%"},"deprecated":{"default":"Any","type":"string","enum":["Any","Opened","None","Any!","Opened!","None!"],"description":"%config.diagnostics.deprecated%"},"missing-parameter":{"default":"Any","type":"string","enum":["Any","Opened","None","Any!","Opened!","None!"],"description":"%config.diagnostics.missing-parameter%"},"global-element":{"default":"None","type":"string","enum":["Any","Opened","None","Any!","Opened!","None!"],"description":"%config.diagnostics.global-element%"},"global-in-nil-env":{"default":"Any","type":"string","enum":["Any","Opened","None","Any!","Opened!","None!"],"description":"%config.diagnostics.global-in-nil-env%"},"incomplete-signature-doc":{"default":"None","type":"string","enum":["Any","Opened","None","Any!","Opened!","None!"],"description":"%config.diagnostics.incomplete-signature-doc%"},"missing-local-export-doc":{"default":"None","type":"string","enum":["Any","Opened","None","Any!","Opened!","None!"],"description":"%config.diagnostics.missing-local-export-doc%"},"inject-field":{"default":"Opened","type":"string","enum":["Any","Opened","None","Any!","Opened!","None!"],"description":"%config.diagnostics.inject-field%"},"invisible":{"default":"Any","type":"string","enum":["Any","Opened","None","Any!","Opened!","None!"],"description":"%config.diagnostics.invisible%"},"missing-return-value":{"default":"Any","type":"string","enum":["Any","Opened","None","Any!","Opened!","None!"],"description":"%config.diagnostics.missing-return-value%"}},"scope":"resource","markdownDescription":"%config.diagnostics.neededFileStatus%","title":"neededFileStatus","type":"object"},"Lua.format.enable":{"default":true,"markdownDescription":"%config.format.enable%","type":"boolean","scope":"resource"},"Lua.diagnostics.disable":{"default":[],"items":{"type":"string","enum":["action-after-return","ambiguity-1","ambiguous-syntax","args-after-dots","assign-type-mismatch","await-in-sync","block-after-else","break-outside","cast-local-type","cast-type-mismatch","circle-doc-class","close-non-object","code-after-break","codestyle-check","count-down-loop","deprecated","different-requires","discard-returns","doc-field-no-class","duplicate-doc-alias","duplicate-doc-field","duplicate-doc-param","duplicate-index","duplicate-set-field","empty-block","err-assign-as-eq","err-c-long-comment","err-comment-prefix","err-do-as-then","err-eq-as-assign","err-esc","err-nonstandard-symbol","err-then-as-do","exp-in-action","global-element","global-in-nil-env","incomplete-signature-doc","index-in-func-name","inject-field","invisible","jump-local-scope","keyword","local-limit","lowercase-global","lua-doc-miss-sign","luadoc-error-diag-mode","luadoc-miss-alias-extends","luadoc-miss-alias-name","luadoc-miss-arg-name","luadoc-miss-cate-name","luadoc-miss-class-extends-name","luadoc-miss-class-name","luadoc-miss-diag-mode","luadoc-miss-diag-name","luadoc-miss-field-extends","luadoc-miss-field-name","luadoc-miss-fun-after-overload","luadoc-miss-generic-name","luadoc-miss-local-name","luadoc-miss-module-name","luadoc-miss-operator-name","luadoc-miss-param-extends","luadoc-miss-param-name","luadoc-miss-see-name","luadoc-miss-sign-name","luadoc-miss-symbol","luadoc-miss-type-name","luadoc-miss-vararg-type","luadoc-miss-version","malformed-number","miss-end","miss-esc-x","miss-exp","miss-exponent","miss-field","miss-loop-max","miss-loop-min","miss-method","miss-name","miss-sep-in-table","miss-space-between","miss-symbol","missing-fields","missing-global-doc","missing-local-export-doc","missing-parameter","missing-return","missing-return-value","name-style-check","need-check-nil","need-paren","nesting-long-mark","newfield-call","newline-call","no-unknown","no-visible-label","not-yieldable","param-type-mismatch","redefined-label","redefined-local","redundant-parameter","redundant-return","redundant-return-value","redundant-value","return-type-mismatch","set-const","spell-check","trailing-space","unbalanced-assignments","undefined-doc-class","undefined-doc-name","undefined-doc-param","undefined-env-child","undefined-field","undefined-global","unexpect-dots","unexpect-efunc-name","unexpect-lfunc-name","unexpect-symbol","unicode-name","unknown-attribute","unknown-cast-variable","unknown-diag-code","unknown-operator","unknown-symbol","unreachable-code","unsupport-symbol","unused-function","unused-label","unused-local","unused-vararg"]},"scope":"resource","markdownDescription":"%config.diagnostics.disable%","type":"array"},"Lua.hint.arrayIndex":{"default":"Auto","markdownDescription":"%config.hint.arrayIndex%","markdownEnumDescriptions":["%config.hint.arrayIndex.Enable%","%config.hint.arrayIndex.Auto%","%config.hint.arrayIndex.Disable%"],"enum":["Enable","Auto","Disable"],"scope":"resource","type":"string"},"Lua.window.statusBar":{"default":true,"markdownDescription":"%config.window.statusBar%","type":"boolean","scope":"resource"},"Lua.type.inferParamType":{"default":false,"markdownDescription":"%config.type.inferParamType%","type":"boolean","scope":"resource"},"Lua.window.progressBar":{"default":true,"markdownDescription":"%config.window.progressBar%","type":"boolean","scope":"resource"},"Lua.type.weakNilCheck":{"default":false,"markdownDescription":"%config.type.weakNilCheck%","type":"boolean","scope":"resource"},"Lua.hint.await":{"default":true,"markdownDescription":"%config.hint.await%","type":"boolean","scope":"resource"},"Lua.type.weakUnionCheck":{"default":false,"markdownDescription":"%config.type.weakUnionCheck%","type":"boolean","scope":"resource"},"Lua.hint.enable":{"default":false,"markdownDescription":"%config.hint.enable%","type":"boolean","scope":"resource"},"Lua.typeFormat.config":{"additionalProperties":false,"properties":{"auto_complete_end":{"default":"true","type":"string","description":"%config.typeFormat.config.auto_complete_end%"},"format_line":{"default":"true","type":"string","description":"%config.typeFormat.config.format_line%"},"auto_complete_table_sep":{"default":"true","type":"string","description":"%config.typeFormat.config.auto_complete_table_sep%"}},"scope":"resource","markdownDescription":"%config.typeFormat.config%","title":"config","type":"object"},"Lua.hint.paramName":{"default":"All","markdownDescription":"%config.hint.paramName%","markdownEnumDescriptions":["%config.hint.paramName.All%","%config.hint.paramName.Literal%","%config.hint.paramName.Disable%"],"enum":["All","Literal","Disable"],"scope":"resource","type":"string"},"Lua.type.castNumberToInteger":{"default":true,"markdownDescription":"%config.type.castNumberToInteger%","type":"boolean","scope":"resource"},"Lua.spell.dict":{"default":[],"items":{"type":"string"},"scope":"resource","markdownDescription":"%config.spell.dict%","type":"array"},"Lua.runtime.special":{"default":{},"additionalProperties":false,"scope":"resource","type":"object","markdownDescription":"%config.runtime.special%","title":"special","patternProperties":{".*":{"default":"require","type":"string","enum":["_G","rawset","rawget","setmetatable","require","dofile","loadfile","pcall","xpcall","assert","error","type","os.exit"]}}},"Lua.runtime.pathStrict":{"default":false,"markdownDescription":"%config.runtime.pathStrict%","type":"boolean","scope":"resource"},"Lua.diagnostics.libraryFiles":{"default":"Opened","markdownDescription":"%config.diagnostics.libraryFiles%","markdownEnumDescriptions":["%config.diagnostics.libraryFiles.Enable%","%config.diagnostics.libraryFiles.Opened%","%config.diagnostics.libraryFiles.Disable%"],"enum":["Enable","Opened","Disable"],"scope":"resource","type":"string"},"Lua.runtime.path":{"default":["?.lua","?\/init.lua"],"items":{"type":"string"},"scope":"resource","markdownDescription":"%config.runtime.path%","type":"array"},"Lua.hint.paramType":{"default":true,"markdownDescription":"%config.hint.paramType%","type":"boolean","scope":"resource"},"Lua.diagnostics.enable":{"default":true,"markdownDescription":"%config.diagnostics.enable%","type":"boolean","scope":"resource"},"Lua.hint.semicolon":{"default":"SameLine","markdownDescription":"%config.hint.semicolon%","markdownEnumDescriptions":["%config.hint.semicolon.All%","%config.hint.semicolon.SameLine%","%config.hint.semicolon.Disable%"],"enum":["All","SameLine","Disable"],"scope":"resource","type":"string"},"Lua.addonManager.enable":{"default":true,"markdownDescription":"%config.addonManager.enable%","type":"boolean","scope":"resource"},"Lua.workspace.checkThirdParty":{"markdownDescription":"%config.workspace.checkThirdParty%","type":["string","boolean"],"scope":"resource"},"Lua.diagnostics.workspaceRate":{"default":100,"markdownDescription":"%config.diagnostics.workspaceRate%","type":"integer","scope":"resource"},"Lua.workspace.ignoreDir":{"default":[".vscode"],"items":{"type":"string"},"scope":"resource","markdownDescription":"%config.workspace.ignoreDir%","type":"array"},"Lua.doc.protectedName":{"default":[],"items":{"type":"string"},"scope":"resource","markdownDescription":"%config.doc.protectedName%","type":"array"},"Lua.hint.setType":{"default":false,"markdownDescription":"%config.hint.setType%","type":"boolean","scope":"resource"},"Lua.workspace.ignoreSubmodules":{"default":true,"markdownDescription":"%config.workspace.ignoreSubmodules%","type":"boolean","scope":"resource"},"Lua.hover.enable":{"default":true,"markdownDescription":"%config.hover.enable%","type":"boolean","scope":"resource"},"Lua.workspace.library":{"default":[],"items":{"type":"string"},"scope":"resource","markdownDescription":"%config.workspace.library%","type":"array"},"Lua.hover.enumsLimit":{"default":5,"markdownDescription":"%config.hover.enumsLimit%","type":"integer","scope":"resource"}},"type":"object"}